dobby_storage/__init__.py
dobby_storage/storage.json
dobby_storage/storage.py
dobby_storage/storage_example.py
dobby_storage/upload_test.txt
dobby_storage-1.0.2.dist-info/LICENSE
dobby_storage-1.0.2.dist-info/METADATA
dobby_storage-1.0.2.dist-info/WHEEL
dobby_storage-1.0.2.dist-info/top_level.txt
dobby_storage-1.0.2.dist-info/RECORD
