Metadata-Version: 2.1
Name: dobby-storage
Version: 1.0.2
Summary: A package for handling various storage options.
Author-email: Ting-Yu Wang <g66341x@gmail.com>
Project-URL: Homepage, https://github.com/Ting-Yu/python-storage-package
Classifier: Programming Language :: Python :: 3
Classifier: License :: OSI Approved :: MIT License
Classifier: Operating System :: OS Independent
Requires-Python: >=3.6
License-File: LICENSE
Requires-Dist: boto3
Requires-Dist: pydrive2
